{
 "mode": "jlens",
 "backend": "jlens-hosted",
 "graph_model": "gemma-2-2b",
 "lens_type": "JACOBIAN_LENS",
 "top_n": 8,
 "start_index": 1,
 "endpoint": "/api/lens/prompt",
 "method_credit": "Jacobian lens: Gurnee et al., Transformer Circuits 2026; reference implementation github.com/anthropics/jacobian-lens; hosted by neuronpedia.org",
 "results": [
  {
   "index": 1,
   "prompts": {
    "clinical": "I have angina, so I need to take my",
    "patient": "My chest is acting up, so I need to take my"
   },
   "target_token": " medication",
   "depth": {
    "clinical": [
     {
      "layer": 0,
      "target_rank": null,
      "match": null,
      "top1": "</strong>"
     },
     {
      "layer": 1,
      "target_rank": null,
      "match": null,
      "top1": "</i>"
     },
     {
      "layer": 2,
      "target_rank": null,
      "match": null,
      "top1": "</strong>"
     },
     {
      "layer": 3,
      "target_rank": null,
      "match": null,
      "top1": "</strong>"
     },
     {
      "layer": 4,
      "target_rank": null,
      "match": null,
      "top1": "</strong>"
     },
     {
      "layer": 5,
      "target_rank": null,
      "match": null,
      "top1": "\u2026\u2019"
     },
     {
      "layer": 6,
      "target_rank": null,
      "match": null,
      "top1": "\u2026\u2019"
     },
     {
      "layer": 7,
      "target_rank": null,
      "match": null,
      "top1": "\u2026\u2019"
     },
     {
      "layer": 8,
      "target_rank": null,
      "match": null,
      "top1": "</em>"
     },
     {
      "layer": 9,
      "target_rank": null,
      "match": null,
      "top1": "\u2026\u2019"
     },
     {
      "layer": 10,
      "target_rank": null,
      "match": null,
      "top1": "\u2026\u2019"
     },
     {
      "layer": 11,
      "target_rank": null,
      "match": null,
      "top1": "RenderAtEndOf"
     },
     {
      "layer": 12,
      "target_rank": null,
      "match": null,
      "top1": "RenderAtEndOf"
     },
     {
      "layer": 13,
      "target_rank": null,
      "match": null,
      "top1": "RenderAtEndOf"
     },
     {
      "layer": 14,
      "target_rank": null,
      "match": null,
      "top1": "RenderAtEndOf"
     },
     {
      "layer": 15,
      "target_rank": null,
      "match": null,
      "top1": "RenderAtEndOf"
     },
     {
      "layer": 16,
      "target_rank": 8,
      "match": "exact",
      "top1": "RenderAtEndOf"
     },
     {
      "layer": 17,
      "target_rank": 3,
      "match": "exact",
      "top1": "RenderAtEndOf"
     },
     {
      "layer": 18,
      "target_rank": 2,
      "match": "exact",
      "top1": " meds"
     },
     {
      "layer": 19,
      "target_rank": 1,
      "match": "exact",
      "top1": " medication"
     },
     {
      "layer": 20,
      "target_rank": 1,
      "match": "exact",
      "top1": " medication"
     },
     {
      "layer": 21,
      "target_rank": 1,
      "match": "exact",
      "top1": " medication"
     },
     {
      "layer": 22,
      "target_rank": 1,
      "match": "exact",
      "top1": " medication"
     },
     {
      "layer": 23,
      "target_rank": 1,
      "match": "exact",
      "top1": " medication"
     },
     {
      "layer": 24,
      "target_rank": 1,
      "match": "exact",
      "top1": " medication"
     },
     {
      "layer": 25,
      "target_rank": 1,
      "match": "exact",
      "top1": " medication"
     }
    ],
    "patient": [
     {
      "layer": 0,
      "target_rank": null,
      "match": null,
      "top1": "</strong>"
     },
     {
      "layer": 1,
      "target_rank": null,
      "match": null,
      "top1": "</i>"
     },
     {
      "layer": 2,
      "target_rank": null,
      "match": null,
      "top1": "</strong>"
     },
     {
      "layer": 3,
      "target_rank": null,
      "match": null,
      "top1": "</strong>"
     },
     {
      "layer": 4,
      "target_rank": null,
      "match": null,
      "top1": "</strong>"
     },
     {
      "layer": 5,
      "target_rank": null,
      "match": null,
      "top1": "\u2026\u2019"
     },
     {
      "layer": 6,
      "target_rank": null,
      "match": null,
      "top1": "</em>"
     },
     {
      "layer": 7,
      "target_rank": null,
      "match": null,
      "top1": "\u2026\u2019"
     },
     {
      "layer": 8,
      "target_rank": null,
      "match": null,
      "top1": "</em>"
     },
     {
      "layer": 9,
      "target_rank": null,
      "match": null,
      "top1": "\u2026\u2019"
     },
     {
      "layer": 10,
      "target_rank": null,
      "match": null,
      "top1": "RenderAtEndOf"
     },
     {
      "layer": 11,
      "target_rank": null,
      "match": null,
      "top1": "RenderAtEndOf"
     },
     {
      "layer": 12,
      "target_rank": null,
      "match": null,
      "top1": "RenderAtEndOf"
     },
     {
      "layer": 13,
      "target_rank": null,
      "match": null,
      "top1": "RenderAtEndOf"
     },
     {
      "layer": 14,
      "target_rank": null,
      "match": null,
      "top1": "RenderAtEndOf"
     },
     {
      "layer": 15,
      "target_rank": null,
      "match": null,
      "top1": "RenderAtEndOf"
     },
     {
      "layer": 16,
      "target_rank": null,
      "match": null,
      "top1": "RenderAtEndOf"
     },
     {
      "layer": 17,
      "target_rank": null,
      "match": null,
      "top1": "RenderAtEndOf"
     },
     {
      "layer": 18,
      "target_rank": 5,
      "match": "exact",
      "top1": "RenderAtEndOf"
     },
     {
      "layer": 19,
      "target_rank": 1,
      "match": "exact",
      "top1": " medication"
     },
     {
      "layer": 20,
      "target_rank": 1,
      "match": "exact",
      "top1": " medication"
     },
     {
      "layer": 21,
      "target_rank": 1,
      "match": "exact",
      "top1": " medication"
     },
     {
      "layer": 22,
      "target_rank": 1,
      "match": "exact",
      "top1": " medication"
     },
     {
      "layer": 23,
      "target_rank": 1,
      "match": "exact",
      "top1": " medication"
     },
     {
      "layer": 24,
      "target_rank": 1,
      "match": "exact",
      "top1": " medication"
     },
     {
      "layer": 25,
      "target_rank": 1,
      "match": "exact",
      "top1": " medication"
     }
    ]
   },
   "parse_status": {
    "clinical": "ok",
    "patient": "ok"
   },
   "first_layer": {
    "clinical": 16,
    "patient": 18
   },
   "last_layer_rank": {
    "clinical": 1,
    "patient": 1
   },
   "patient_depth_class": "retained"
  },
  {
   "index": 2,
   "prompts": {
    "clinical": "I suspect I have influenza, so I should get some",
    "patient": "I think I'm coming down with something, so I should get some"
   },
   "target_token": " antivirals",
   "depth": {
    "clinical": [
     {
      "layer": 0,
      "target_rank": null,
      "match": null,
      "top1": "\u00c3"
     },
     {
      "layer": 1,
      "target_rank": null,
      "match": null,
      "top1": "\u2033"
     },
     {
      "layer": 2,
      "target_rank": null,
      "match": null,
      "top1": " \u00a8"
     },
     {
      "layer": 3,
      "target_rank": null,
      "match": null,
      "top1": " \u00a8"
     },
     {
      "layer": 4,
      "target_rank": null,
      "match": null,
      "top1": " \u00a8"
     },
     {
      "layer": 5,
      "target_rank": null,
      "match": null,
      "top1": "\u00c3"
     },
     {
      "layer": 6,
      "target_rank": null,
      "match": null,
      "top1": " stuff"
     },
     {
      "layer": 7,
      "target_rank": null,
      "match": null,
      "top1": "\"\"\""
     },
     {
      "layer": 8,
      "target_rank": null,
      "match": null,
      "top1": "\"\"\""
     },
     {
      "layer": 9,
      "target_rank": null,
      "match": null,
      "top1": "\"\"\""
     },
     {
      "layer": 10,
      "target_rank": null,
      "match": null,
      "top1": ">`;"
     },
     {
      "layer": 11,
      "target_rank": null,
      "match": null,
      "top1": "?\u201d."
     },
     {
      "layer": 12,
      "target_rank": null,
      "match": null,
      "top1": "RenderAtEndOf"
     },
     {
      "layer": 13,
      "target_rank": null,
      "match": null,
      "top1": "RenderAtEndOf"
     },
     {
      "layer": 14,
      "target_rank": null,
      "match": null,
      "top1": "RenderAtEndOf"
     },
     {
      "layer": 15,
      "target_rank": null,
      "match": null,
      "top1": "RenderAtEndOf"
     },
     {
      "layer": 16,
      "target_rank": null,
      "match": null,
      "top1": "AndEndTag"
     },
     {
      "layer": 17,
      "target_rank": null,
      "match": null,
      "top1": "AndEndTag"
     },
     {
      "layer": 18,
      "target_rank": null,
      "match": null,
      "top1": "+#+#"
     },
     {
      "layer": 19,
      "target_rank": 8,
      "match": "prefix",
      "top1": " medication"
     },
     {
      "layer": 20,
      "target_rank": 3,
      "match": "prefix",
      "top1": " medication"
     },
     {
      "layer": 21,
      "target_rank": 3,
      "match": "prefix",
      "top1": " medication"
     },
     {
      "layer": 22,
      "target_rank": 2,
      "match": "prefix",
      "top1": " medication"
     },
     {
      "layer": 23,
      "target_rank": 6,
      "match": "prefix",
      "top1": " medication"
     },
     {
      "layer": 24,
      "target_rank": 5,
      "match": "prefix",
      "top1": " medication"
     },
     {
      "layer": 25,
      "target_rank": null,
      "match": null,
      "top1": " rest"
     }
    ],
    "patient": [
     {
      "layer": 0,
      "target_rank": null,
      "match": null,
      "top1": "\u00c3"
     },
     {
      "layer": 1,
      "target_rank": null,
      "match": null,
      "top1": "\"`"
     },
     {
      "layer": 2,
      "target_rank": null,
      "match": null,
      "top1": " \u00a8"
     },
     {
      "layer": 3,
      "target_rank": null,
      "match": null,
      "top1": " \u00a8"
     },
     {
      "layer": 4,
      "target_rank": null,
      "match": null,
      "top1": " \u00a8"
     },
     {
      "layer": 5,
      "target_rank": null,
      "match": null,
      "top1": "\u00c3"
     },
     {
      "layer": 6,
      "target_rank": null,
      "match": null,
      "top1": " stuff"
     },
     {
      "layer": 7,
      "target_rank": null,
      "match": null,
      "top1": " maybe"
     },
     {
      "layer": 8,
      "target_rank": null,
      "match": null,
      "top1": " kids"
     },
     {
      "layer": 9,
      "target_rank": null,
      "match": null,
      "top1": " kids"
     },
     {
      "layer": 10,
      "target_rank": null,
      "match": null,
      "top1": " kids"
     },
     {
      "layer": 11,
      "target_rank": null,
      "match": null,
      "top1": "RenderAtEndOf"
     },
     {
      "layer": 12,
      "target_rank": null,
      "match": null,
      "top1": "RenderAtEndOf"
     },
     {
      "layer": 13,
      "target_rank": null,
      "match": null,
      "top1": "RenderAtEndOf"
     },
     {
      "layer": 14,
      "target_rank": null,
      "match": null,
      "top1": "RenderAtEndOf"
     },
     {
      "layer": 15,
      "target_rank": null,
      "match": null,
      "top1": "RenderAtEndOf"
     },
     {
      "layer": 16,
      "target_rank": null,
      "match": null,
      "top1": "RenderAtEndOf"
     },
     {
      "layer": 17,
      "target_rank": null,
      "match": null,
      "top1": "+#+#"
     },
     {
      "layer": 18,
      "target_rank": null,
      "match": null,
      "top1": " sleep"
     },
     {
      "layer": 19,
      "target_rank": null,
      "match": null,
      "top1": " sleep"
     },
     {
      "layer": 20,
      "target_rank": null,
      "match": null,
      "top1": " sleep"
     },
     {
      "layer": 21,
      "target_rank": null,
      "match": null,
      "top1": " sleep"
     },
     {
      "layer": 22,
      "target_rank": null,
      "match": null,
      "top1": " sleep"
     },
     {
      "layer": 23,
      "target_rank": null,
      "match": null,
      "top1": " medicine"
     },
     {
      "layer": 24,
      "target_rank": null,
      "match": null,
      "top1": " sleep"
     },
     {
      "layer": 25,
      "target_rank": null,
      "match": null,
      "top1": " rest"
     }
    ]
   },
   "parse_status": {
    "clinical": "ok",
    "patient": "ok"
   },
   "first_layer": {
    "clinical": 19,
    "patient": null
   },
   "last_layer_rank": {
    "clinical": null,
    "patient": null
   },
   "patient_depth_class": "absent"
  }
 ]
}
